{"ts":"2021-09-01T01:02:28.941Z","hut":{"id":346,"active":false,"name":"ZZZ TEST Monbijouhütte, SAC GS","info":{"de_AT":["Hüttenwirt/in: Daniel Fernandez TEST","Hüttentelefonnummer: 000 000 00 00","Schlafplätze gesamt: 10","Höhe ü. Meer: 666 m","Koordinaten: XXX.XXX / YYY.YYY"],"en":["Hut warden(s): Daniel Fernandez TEST","Hut phone number: 000 000 00 00","Total sleeping places: 10","Height above sea level: 666 m","Coordinates: XXX.XXX / YYY.YYY"],"it":["Gestore rifugio: Daniel Fernandez TEST","No. telefonico del rifugio: 000 000 00 00","Posti letto totali: 10","Altitudine: 666 m","Coordinate: XXX.XXX / YYY.YYY"],"sl":["Oskrbnik(i): Daniel Fernandez TEST","Telefonska številka koče: 000 000 00 00","Vsa ležišča: 10","Nadmorska višina: 666 m","Koordinate: XXX.XXX / YYY.YYY"]},"desc":{"de_AT":null,"en":null,"it":null,"sl":null},"bedCategories":{"de_AT":[],"en":[],"it":[],"sl":[]},"calendar":{},"error":{"de_AT":"Diese Hütte ist nicht freigeschaltet. Sie können zur Zeit keine Reservierung erfassen. Bitte nehmen Sie Kontakt mit dem Administrator auf.","en":"This hut profile is not activated. Bookings cannot be entered at the moment. Please contact the administrator.","it":"Questo rifugio è bloccato. In questo momento non è possibile eseguire prenotazioni. Si prega di contattare direttamente l'amministratore.","sl":"Profil te koče ni aktiviran. Rezervacij trenutno ni možno vnašati. Prosimo, obrnite se na administratorja."}}}
