{"ts":"2021-08-03T01:02:44.705Z","hut":{"id":376,"active":false,"name":"Berggasthaus Gitschenen","info":{"de_AT":["Hüttenwirt/in: Brigitta & Dani","Hüttentelefonnummer: +41 41 878 11 58","Schlafplätze gesamt: 50","Höhe ü. Meer: 1550 m","Koordinaten: 695.488 / 198.992"],"en":["Hut warden(s): Brigitta & Dani","Hut phone number: +41 41 878 11 58","Total sleeping places: 50","Height above sea level: 1550 m","Coordinates: 695.488 / 198.992"],"it":["Gestore rifugio: Brigitta & Dani","No. telefonico del rifugio: +41 41 878 11 58","Posti letto totali: 50","Altitudine: 1550 m","Coordinate: 695.488 / 198.992"],"sl":["Oskrbnik(i): Brigitta & Dani","Telefonska številka koče: +41 41 878 11 58","Vsa ležišča: 50","Nadmorska višina: 1550 m","Koordinate: 695.488 / 198.992"]},"desc":{"de_AT":null,"en":null,"it":null,"sl":null},"bedCategories":{"de_AT":[],"en":[],"it":[],"sl":[]},"calendar":{},"error":{"de_AT":"Diese Hütte ist nicht freigeschaltet. Sie können zur Zeit keine Reservierung erfassen. Bitte nehmen Sie Kontakt mit dem Administrator auf.","en":"This hut profile is not activated. Bookings cannot be entered at the moment. Please contact the administrator.","it":"Questo rifugio è bloccato. In questo momento non è possibile eseguire prenotazioni. Si prega di contattare direttamente l'amministratore.","sl":"Profil te koče ni aktiviran. Rezervacij trenutno ni možno vnašati. Prosimo, obrnite se na administratorja."}}}
