{"ts":"2021-08-01T17:53:27.592Z","huts":[{"id":145,"name":"Riemannhaus, Sektion Ingolstadt","active":true},{"id":null,"name":"Riemannhaus, Sektion Ingolstadt","active":false},{"id":null,"name":"Riemannhaus, Sektion Ingolstadt","active":false},{"id":null,"name":"Riemannhaus, Sektion Ingolstadt","active":false},{"id":null,"name":"Riemannhaus, Sektion Ingolstadt","active":false},{"id":null,"name":"Riemannhaus, Sektion Ingolstadt","active":false},{"id":null,"name":"Riemannhaus, Sektion Ingolstadt","active":false},{"id":null,"name":"Riemannhaus, Sektion Ingolstadt","active":false},{"id":null,"name":"Riemannhaus, Sektion Ingolstadt","active":false},{"id":null,"name":"Riemannhaus, Sektion Ingolstadt","active":false},{"id":null,"name":"Riemannhaus, Sektion Ingolstadt","active":false},{"id":null,"name":"Riemannhaus, Sektion Ingolstadt","active":false},{"id":null,"name":"Riemannhaus, Sektion Ingolstadt","active":false},{"id":null,"name":"Riemannhaus, Sektion Ingolstadt","active":false},{"id":null,"name":"Riemannhaus, Sektion Ingolstadt","active":false},{"id":null,"name":"Riemannhaus, Sektion Ingolstadt","active":false},{"id":null,"name":"Riemannhaus, Sektion Ingolstadt","active":false},{"id":null,"name":"Riemannhaus, Sektion Ingolstadt","active":false},{"id":null,"name":"Riemannhaus, Sektion Ingolstadt","active":false}]}
